jupyter_rstudio_singularity/__init__.py
jupyter_rstudio_singularity/cli.py
jupyter_rstudio_singularity/jupyter_rstudio_singularity.py
jupyter_rstudio_singularity/utils/__init__.py
jupyter_rstudio_singularity/utils/logging.py
jupyter_rstudio_singularity-0.1.0.dist-info/LICENSE
jupyter_rstudio_singularity-0.1.0.dist-info/METADATA
jupyter_rstudio_singularity-0.1.0.dist-info/WHEEL
jupyter_rstudio_singularity-0.1.0.dist-info/entry_points.txt
jupyter_rstudio_singularity-0.1.0.dist-info/top_level.txt
jupyter_rstudio_singularity-0.1.0.dist-info/RECORD
