Metadata-Version: 2.1
Name: jupyter-rstudio-singularity
Version: 0.1.0
Summary: Launch RStudio with Singularity from the command line.
Home-page: https://github.com/dabble-of-devops-bioanalyze/jupyter_rstudio_singularity
Author: Jillian Rowe
Author-email: jillian@dabbleofdevops.com
License: Apache Software License 2.0
Keywords: jupyter_rstudio_singularity
Classifier: Development Status :: 2 - Pre-Alpha
Classifier: Intended Audience :: Developers
Classifier: License :: OSI Approved :: Apache Software License
Classifier: Natural Language :: English
Classifier: Programming Language :: Python :: 3
Classifier: Programming Language :: Python :: 3.6
Classifier: Programming Language :: Python :: 3.7
Classifier: Programming Language :: Python :: 3.8
Requires-Python: >=3.6
License-File: LICENSE
Requires-Dist: Click (>=7.0)
Requires-Dist: typer[all]
Requires-Dist: prefect (>2)
Requires-Dist: prefect-shell
Requires-Dist: colorlog
